{
    "ui_description": "UI element 0: {\"index\": 0, \"is_clickable\": True, \"is_long_clickable\": False, \"is_editable\": False, \"is_selected\": False, \"is_checked\": False}\nUI element 1: {\"index\": 1, \"is_clickable\": True, \"is_long_clickable\": False, \"is_editable\": False, \"is_selected\": False, \"is_checked\": False}\nUI element 2: {\"index\": 2, \"is_clickable\": True, \"is_long_clickable\": False, \"is_editable\": False, \"is_selected\": False, \"is_checked\": False}\nUI element 3: {\"index\": 3, \"is_clickable\": True, \"is_long_clickable\": False, \"is_editable\": False, \"is_selected\": False, \"is_checked\": False}\nUI element 4: {\"index\": 4, \"is_clickable\": True, \"is_long_clickable\": False, \"is_editable\": False, \"is_selected\": False, \"is_checked\": False}\nUI element 5: {\"index\": 5, \"is_clickable\": True, \"is_long_clickable\": False, \"is_editable\": False, \"is_selected\": False, \"is_checked\": False}\nUI element 6: {\"index\": 6, \"is_clickable\": True, \"is_long_clickable\": False, \"is_editable\": False, \"is_selected\": False, \"is_checked\": False}\nUI element 7: {\"index\": 7, \"is_clickable\": True, \"is_long_clickable\": False, \"is_editable\": False, \"is_focusable\": True, \"is_selected\": False, \"is_checked\": False}\nUI element 8: {\"index\": 8, \"is_clickable\": True, \"is_long_clickable\": False, \"is_editable\": False, \"is_selected\": False, \"is_checked\": False}\nUI element 9: {\"index\": 9, \"is_clickable\": True, \"is_long_clickable\": False, \"is_editable\": False, \"is_selected\": False, \"is_checked\": False}\nUI element 10: {\"index\": 10, \"is_clickable\": True, \"is_long_clickable\": False, \"is_editable\": False, \"is_selected\": False, \"is_checked\": False}\nUI element 11: {\"index\": 11, \"is_clickable\": True, \"is_long_clickable\": False, \"is_editable\": False, \"is_selected\": False, \"is_checked\": False}\nUI element 12: {\"index\": 12, \"text\": \"Couldn't sign in\", \"is_clickable\": True, \"is_long_clickable\": False, \"is_editable\": False, \"is_selected\": False, \"is_checked\": False}\nUI element 13: {\"index\": 13, \"is_clickable\": True, \"is_long_clickable\": False, \"is_editable\": False, \"is_selected\": False, \"is_checked\": False}\nUI element 14: {\"index\": 14, \"is_clickable\": True, \"is_long_clickable\": False, \"is_editable\": False, \"is_selected\": False, \"is_checked\": False}\nUI element 15: {\"index\": 15, \"is_clickable\": True, \"is_long_clickable\": False, \"is_editable\": False, \"is_selected\": False, \"is_checked\": False}\n"
}