[
    {
        "ui_description": "UI element 0: {\"index\": 0, \"is_clickable\": False, \"is_long_clickable\": False, \"is_editable\": False, \"is_selected\": False, \"is_checked\": False}",
        "ui_bbox": [
            0,
            1080,
            0,
            2400
        ]
    },
    {
        "ui_description": "UI element 1: {\"index\": 1, \"is_clickable\": False, \"is_long_clickable\": False, \"is_editable\": False, \"is_selected\": False, \"is_checked\": False}",
        "ui_bbox": [
            0,
            1080,
            0,
            2400
        ]
    },
    {
        "ui_description": "UI element 2: {\"index\": 2, \"is_clickable\": False, \"is_long_clickable\": False, \"is_editable\": False, \"is_selected\": False, \"is_checked\": False}",
        "ui_bbox": [
            0,
            1080,
            0,
            2400
        ]
    },
    {
        "ui_description": "UI element 3: {\"index\": 3, \"is_clickable\": False, \"is_long_clickable\": False, \"is_editable\": False, \"is_selected\": False, \"is_checked\": False}",
        "ui_bbox": [
            0,
            1080,
            0,
            2400
        ]
    },
    {
        "ui_description": "UI element 4: {\"index\": 4, \"is_clickable\": False, \"is_long_clickable\": False, \"is_editable\": False, \"is_selected\": False, \"is_checked\": False}",
        "ui_bbox": [
            0,
            1080,
            0,
            2400
        ]
    },
    {
        "ui_description": "UI element 5: {\"index\": 5, \"is_clickable\": False, \"is_long_clickable\": False, \"is_editable\": False, \"is_selected\": False, \"is_checked\": False}",
        "ui_bbox": [
            0,
            1080,
            0,
            2400
        ]
    },
    {
        "ui_description": "UI element 6: {\"index\": 6, \"is_clickable\": False, \"is_long_clickable\": False, \"is_editable\": False, \"is_selected\": False, \"is_checked\": False}",
        "ui_bbox": [
            0,
            1080,
            0,
            2400
        ]
    },
    {
        "ui_description": "UI element 7: {\"index\": 7, \"is_clickable\": False, \"is_long_clickable\": False, \"is_editable\": False, \"is_selected\": False, \"is_checked\": False}",
        "ui_bbox": [
            0,
            1080,
            0,
            2400
        ]
    },
    {
        "ui_description": "UI element 8: {\"index\": 8, \"is_clickable\": False, \"is_long_clickable\": False, \"is_editable\": False, \"is_selected\": False, \"is_checked\": False}",
        "ui_bbox": [
            0,
            1080,
            0,
            2400
        ]
    },
    {
        "ui_description": "UI element 9: {\"index\": 9, \"is_clickable\": False, \"is_long_clickable\": False, \"is_editable\": False, \"is_focusable\": True, \"is_selected\": False, \"is_checked\": False}",
        "ui_bbox": [
            0,
            1080,
            0,
            2400
        ]
    },
    {
        "ui_description": "UI element 10: {\"index\": 10, \"is_clickable\": True, \"is_long_clickable\": False, \"is_editable\": False, \"is_focusable\": True, \"is_selected\": False, \"is_checked\": False}",
        "ui_bbox": [
            0,
            1080,
            296,
            552
        ]
    },
    {
        "ui_description": "UI element 11: {\"index\": 11, \"is_clickable\": False, \"is_long_clickable\": False, \"is_editable\": False, \"is_selected\": False, \"is_checked\": False}",
        "ui_bbox": [
            42,
            874,
            296,
            552
        ]
    },
    {
        "ui_description": "UI element 12: {\"index\": 12, \"text\": \"Suggest message reminders\", \"is_clickable\": False, \"is_long_clickable\": False, \"is_editable\": False, \"is_selected\": False, \"is_checked\": False}",
        "ui_bbox": [
            42,
            588,
            338,
            398
        ]
    },
    {
        "ui_description": "UI element 13: {\"index\": 13, \"text\": \"Messages that may need a reply or follow up will move to the top\", \"is_clickable\": False, \"is_long_clickable\": False, \"is_editable\": False, \"is_selected\": False, \"is_checked\": False}",
        "ui_bbox": [
            42,
            874,
            398,
            510
        ]
    },
    {
        "ui_description": "UI element 14: {\"index\": 14, \"is_clickable\": False, \"is_long_clickable\": False, \"is_editable\": False, \"is_selected\": False, \"is_checked\": False}",
        "ui_bbox": [
            874,
            1038,
            296,
            552
        ]
    },
    {
        "ui_description": "UI element 15: {\"index\": 15, \"is_clickable\": False, \"is_long_clickable\": False, \"is_editable\": False, \"is_selected\": False, \"is_checked\": True}",
        "ui_bbox": [
            916,
            1038,
            388,
            459
        ]
    },
    {
        "ui_description": "UI element 16: {\"index\": 16, \"is_clickable\": True, \"is_long_clickable\": False, \"is_editable\": False, \"is_focusable\": True, \"is_selected\": False, \"is_checked\": False}",
        "ui_bbox": [
            0,
            1080,
            552,
            808
        ]
    },
    {
        "ui_description": "UI element 17: {\"index\": 17, \"is_clickable\": False, \"is_long_clickable\": False, \"is_editable\": False, \"is_selected\": False, \"is_checked\": False}",
        "ui_bbox": [
            42,
            874,
            552,
            808
        ]
    },
    {
        "ui_description": "UI element 18: {\"index\": 18, \"text\": \"Birthday reminders\", \"is_clickable\": False, \"is_long_clickable\": False, \"is_editable\": False, \"is_selected\": False, \"is_checked\": False}",
        "ui_bbox": [
            42,
            408,
            594,
            654
        ]
    },
    {
        "ui_description": "UI element 19: {\"index\": 19, \"text\": \"Get reminders for birthdays you've added to contacts on your device\", \"is_clickable\": False, \"is_long_clickable\": False, \"is_editable\": False, \"is_selected\": False, \"is_checked\": False}",
        "ui_bbox": [
            42,
            874,
            654,
            766
        ]
    },
    {
        "ui_description": "UI element 20: {\"index\": 20, \"is_clickable\": False, \"is_long_clickable\": False, \"is_editable\": False, \"is_selected\": False, \"is_checked\": False}",
        "ui_bbox": [
            874,
            1038,
            552,
            808
        ]
    },
    {
        "ui_description": "UI element 21: {\"index\": 21, \"is_clickable\": False, \"is_long_clickable\": False, \"is_editable\": False, \"is_selected\": False, \"is_checked\": False}",
        "ui_bbox": [
            916,
            1038,
            644,
            715
        ]
    },
    {
        "ui_description": "UI element 22: {\"index\": 22, \"text\": \"More about nudges\", \"is_clickable\": True, \"is_long_clickable\": False, \"is_editable\": False, \"is_focusable\": True, \"is_selected\": False, \"is_checked\": False}",
        "ui_bbox": [
            0,
            1080,
            808,
            943
        ]
    },
    {
        "ui_description": "UI element 23: {\"index\": 23, \"is_clickable\": False, \"is_long_clickable\": False, \"is_editable\": False, \"is_selected\": False, \"is_checked\": False}",
        "ui_bbox": [
            0,
            1080,
            128,
            296
        ]
    },
    {
        "ui_description": "UI element 24: {\"index\": 24, \"content_description\": \"Navigate up\", \"is_clickable\": True, \"is_long_clickable\": False, \"is_editable\": False, \"is_focusable\": True, \"is_selected\": False, \"is_checked\": False}",
        "ui_bbox": [
            0,
            147,
            128,
            296
        ]
    },
    {
        "ui_description": "UI element 25: {\"index\": 25, \"text\": \"Nudges\", \"is_clickable\": False, \"is_long_clickable\": False, \"is_editable\": False, \"is_selected\": False, \"is_checked\": False}",
        "ui_bbox": [
            157,
            320,
            182,
            242
        ]
    },
    {
        "ui_description": "UI element 26: {\"index\": 26, \"is_clickable\": False, \"is_long_clickable\": False, \"is_editable\": False, \"is_selected\": False, \"is_checked\": False}",
        "ui_bbox": [
            0,
            1080,
            0,
            128
        ]
    },
    {
        "ui_description": "UI element 27: {\"index\": 27, \"is_clickable\": False, \"is_long_clickable\": False, \"is_editable\": False, \"is_selected\": False, \"is_checked\": False}",
        "ui_bbox": [
            0,
            1080,
            2337,
            2400
        ]
    }
]